molecule_vagrant/__init__.py
molecule_vagrant/driver.py
molecule_vagrant/cookiecutter/cookiecutter.json
molecule_vagrant/cookiecutter/{{cookiecutter.molecule_directory}}/{{cookiecutter.scenario_name}}/INSTALL.rst
molecule_vagrant/cookiecutter/{{cookiecutter.molecule_directory}}/{{cookiecutter.scenario_name}}/converge.yml
molecule_vagrant/modules/__init__.py
molecule_vagrant/modules/vagrant.py
molecule_vagrant/playbooks/create.yml
molecule_vagrant/playbooks/destroy.yml
molecule_vagrant/playbooks/prepare.yml
molecule_vagrant/test/__init__.py
molecule_vagrant/test/test_driver.py
molecule_vagrant/test/functional/__init__.py
molecule_vagrant/test/functional/conftest.py
molecule_vagrant/test/functional/test_func.py
molecule_vagrant/test/scenarios/molecule/config_options/converge.yml
molecule_vagrant/test/scenarios/molecule/config_options/molecule.yml
molecule_vagrant/test/scenarios/molecule/config_options/verify.yml
molecule_vagrant/test/scenarios/molecule/default/converge.yml
molecule_vagrant/test/scenarios/molecule/default/molecule.yml
molecule_vagrant/test/scenarios/molecule/default-compat/converge.yml
molecule_vagrant/test/scenarios/molecule/default-compat/create.yml
molecule_vagrant/test/scenarios/molecule/default-compat/destroy.yml
molecule_vagrant/test/scenarios/molecule/default-compat/molecule.yml
molecule_vagrant/test/scenarios/molecule/hostname/converge.yml
molecule_vagrant/test/scenarios/molecule/hostname/molecule.yml
molecule_vagrant/test/scenarios/molecule/hostname/verify.yml
molecule_vagrant/test/scenarios/molecule/invalid/converge.yml
molecule_vagrant/test/scenarios/molecule/invalid/molecule.yml
molecule_vagrant/test/scenarios/molecule/multi-node/converge.yml
molecule_vagrant/test/scenarios/molecule/multi-node/molecule.yml
molecule_vagrant/test/scenarios/molecule/multi-node/verify.yml
molecule_vagrant/test/scenarios/molecule/network/converge.yml
molecule_vagrant/test/scenarios/molecule/network/molecule.yml
molecule_vagrant-2.0.0.dist-info/LICENSE
molecule_vagrant-2.0.0.dist-info/METADATA
molecule_vagrant-2.0.0.dist-info/WHEEL
molecule_vagrant-2.0.0.dist-info/entry_points.txt
molecule_vagrant-2.0.0.dist-info/top_level.txt
molecule_vagrant-2.0.0.dist-info/RECORD
