Metadata-Version: 2.1
Name: molecule-vagrant
Version: 2.0.0
Summary: Vagrant Molecule Plugin :: run molecule tests using Vagrant
Home-page: https://github.com/ansible-community/molecule-vagrant
Author: Sorin Sbarnea
Author-email: sorin.sbarnea@gmail.com
Maintainer: Sorin Sbarnea
Maintainer-email: sorin.sbarnea@gmail.com
License: MIT
Project-URL: Bug Tracker, https://github.com/ansible-community/molecule-vagrant/issues
Project-URL: Release Management, https://github.com/ansible-community/molecule-vagrant/releases
Project-URL: CI: Zuul, https://dashboard.zuul.ansible.com/t/ansible/builds?project=ansible-community/molecule-vagrant
Project-URL: Source Code, https://github.com/ansible-community/molecule-vagrant
Keywords: ansible,roles,testing,molecule,plugin,vagrant
Classifier: Development Status :: 5 - Production/Stable
Classifier: Environment :: Console
Classifier: Intended Audience :: Developers
Classifier: Intended Audience :: Information Technology
Classifier: Intended Audience :: System Administrators
Classifier: License :: OSI Approved :: MIT License
Classifier: Natural Language :: English
Classifier: Operating System :: OS Independent
Classifier: Programming Language :: Python :: 3
Classifier: Programming Language :: Python :: 3.9
Classifier: Programming Language :: Python :: 3.10
Classifier: Topic :: System :: Systems Administration
Classifier: Topic :: Utilities
Requires-Python: >=3.9
License-File: LICENSE
Requires-Dist: molecule (>=3.4.1)
Requires-Dist: pyyaml (>=5.1)
Requires-Dist: Jinja2 (>=2.11.3)
Requires-Dist: selinux
Requires-Dist: python-vagrant (>=1.0.0)
Provides-Extra: test
Requires-Dist: molecule[test] ; extra == 'test'
